fl_operation_gm/__init__.py
fl_operation_gm/example.py
fl_operation_gm-0.0.9.dist-info/LICENSE.txt
fl_operation_gm-0.0.9.dist-info/METADATA
fl_operation_gm-0.0.9.dist-info/WHEEL
fl_operation_gm-0.0.9.dist-info/top_level.txt
fl_operation_gm-0.0.9.dist-info/RECORD
