Metadata-Version: 2.2
Name: fl_operation_gm
Version: 0.0.9
Summary: File operation handler CLI
Author: Example Author
Author-email: Dmitry Author <author@example.com>
Classifier: Programming Language :: Python :: 3
Classifier: License :: OSI Approved :: MIT License
Classifier: Operating System :: OS Independent
Requires-Python: >=3.9
License-File: LICENSE.txt
Dynamic: author
Dynamic: requires-python
